{
  "warnings" : [ ],
  "files" : [ "report.json", "untyped_program.evm-testcases_taint_example_example.sol().json" ],
  "info" : {
    "cfgs" : "1",
    "duration" : "326ms",
    "end" : "2024-12-11T14:35:57.428+01:00",
    "expressions" : "2",
    "files" : "1",
    "globals" : "0",
    "members" : "1",
    "programs" : "1",
    "start" : "2024-12-11T14:35:57.102+01:00",
    "statements" : "4",
    "units" : "0",
    "version" : "0.1",
    "warnings" : "0"
  },
  "configuration" : {
    "analysisGraphs" : "NONE",
    "descendingPhaseType" : "NONE",
    "dumpForcesUnwinding" : "false",
    "fixpointWorkingSet" : "DuplicateFreeFIFOWorkingSet",
    "glbThreshold" : "5",
    "hotspots" : "unset",
    "jsonOutput" : "true",
    "openCallPolicy" : "WorstCasePolicy",
    "optimize" : "false",
    "recursionWideningThreshold" : "5",
    "semanticChecks" : "",
    "serializeInputs" : "false",
    "serializeResults" : "true",
    "syntacticChecks" : "",
    "useWideningPoints" : "false",
    "wideningThreshold" : "5",
    "workdir" : "evm-outputs/taint/example"
  }
}